dict_and_union_with/__init__.py
dict_and_union_with/dict_union_with.py
dict_and_union_with-1.0.0.dist-info/LICENSE
dict_and_union_with-1.0.0.dist-info/METADATA
dict_and_union_with-1.0.0.dist-info/WHEEL
dict_and_union_with-1.0.0.dist-info/top_level.txt
dict_and_union_with-1.0.0.dist-info/RECORD
