Metadata-Version: 2.1
Name: dict-and-union-with
Version: 1.0.0
Summary: A manual solution to the union operation on dictionaries, in Python
Home-page: https://github.com/Whoeza/dict_and_union_with
Author: Whoeza
License: GNU GPLv3
Project-URL: Bug Tracker, https://github.com/Whoeza/dict_and_union_with/issues
Classifier: Intended Audience :: Developers
Classifier: License :: OSI Approved :: GNU General Public License v3 (GPLv3)
Classifier: Operating System :: OS Independent
Classifier: Programming Language :: Python :: 3
Requires-Python: >=3.6
License-File: LICENSE
